skilearn22/__init__.py
skilearn22/skilearn22.py
skilearn22-0.2.2.dist-info/METADATA
skilearn22-0.2.2.dist-info/WHEEL
skilearn22-0.2.2.dist-info/top_level.txt
skilearn22-0.2.2.dist-info/RECORD
