Metadata-Version: 2.2
Name: skilearn22
Version: 0.2.2
Summary: zxczxczxc
Author: asd dasd
Requires-Python: >=3.6
Requires-Dist: pyperclip
Dynamic: author
Dynamic: requires-dist
Dynamic: requires-python
Dynamic: summary
